superjacob/__init__.py
superjacob/expression.py
superjacob/operations.py
superjacob/reverse.py
superjacob/superjacob.py
superjacob-0.0.1.dist-info/LICENSE
superjacob-0.0.1.dist-info/METADATA
superjacob-0.0.1.dist-info/WHEEL
superjacob-0.0.1.dist-info/top_level.txt
superjacob-0.0.1.dist-info/RECORD
