Metadata-Version: 2.1
Name: superjacob
Version: 0.0.1
Summary: Yet another autodiff package (YAAP
Home-page: https://github.com/ADMonsters/cs207-FinalProject
Author: Benjamin Levy, Mark Miao, Zhenru Wang, Kidus Negesse
License: UNKNOWN
Platform: UNKNOWN
Classifier: Programming Language :: Python :: 3
Classifier: License :: OSI Approved :: MIT License
Classifier: Operating System :: OS Independent
Requires-Python: >=3.5
